my_first_package_xavier_lai_cways/__init__.py
my_first_package_xavier_lai_cways/hello.py
my_first_package_xavier_lai_cways-0.1.0.dist-info/METADATA
my_first_package_xavier_lai_cways-0.1.0.dist-info/WHEEL
my_first_package_xavier_lai_cways-0.1.0.dist-info/RECORD
