Metadata-Version: 2.1
Name: my-first-package-xavier-lai-cways
Version: 0.1.0
Summary: 
Author: xavier.lai
Author-email: xavier.lai@c-ways.com
Requires-Python: >=3.10,<4.0
Classifier: Programming Language :: Python :: 3
Classifier: Programming Language :: Python :: 3.10
Classifier: Programming Language :: Python :: 3.11
Classifier: Programming Language :: Python :: 3.12
Requires-Dist: pandas (>=2.1.4,<3.0.0)
